sleipnir/__init__.py
sleipnir/__init__.pyi
sleipnir/_sleipnir.abi3.so
sleipnir/py.typed
sleipnir/autodiff/__init__.py
sleipnir/autodiff/__init__.pyi
sleipnir/optimization/__init__.py
sleipnir/optimization/__init__.pyi
sleipnirgroup_jormungandr-0.3.5.dist-info/METADATA
sleipnirgroup_jormungandr-0.3.5.dist-info/WHEEL
sleipnirgroup_jormungandr-0.3.5.dist-info/entry_points.txt
sleipnirgroup_jormungandr-0.3.5.dist-info/licenses/LICENSE.txt
sleipnirgroup_jormungandr-0.3.5.dist-info/RECORD
