Metadata-Version: 2.4
Name: sleipnirgroup-jormungandr
Version: 0.3.5
Summary: Reverse mode autodiff library and NLP solver DSL
License-Expression: BSD-3-Clause
License-File: LICENSE.txt
Project-URL: Documentation, https://sleipnirgroup.github.io/Sleipnir/
Requires-Python: >=3.12
Requires-Dist: matplotlib
Requires-Dist: numpy
Requires-Dist: scipy
